loglibrary_x21171581/__init__.py
loglibrary_x21171581/level.py
loglibrary_x21171581/log_record.py
loglibrary_x21171581/logger.py
loglibrary_x21171581/notifier.py
loglibrary_x2117158-0.0.1.dist-info/WHEEL
loglibrary_x2117158-0.0.1.dist-info/METADATA
loglibrary_x2117158-0.0.1.dist-info/licenses/LICENSE
loglibrary_x2117158-0.0.1.dist-info/RECORD
